[
    {
        "sku": "CW2288-111",
        "name": "Nike Air Force 1 '07",
        "price": 110.00,
        "description": "The radiance lives on in the Nike Air Force 1 ’07, the b-ball OG that puts a fresh spin on what you know best: durably stitched overlays, clean finishes and the perfect amount of flash to make you shine.",
        "images": ["https://static.nike.com/a/images/t_PDP_864_v1/f_auto,b_rgb:f5f5f5/b7d9211c-26e7-431a-ac24-b0540fb3c00f/air-force-1-07-mens-shoes-5QFp5Z.png"],
        "category": "Men",
        "style": "Men's Shoe",
        "isNew": false,
        "onSale": false,
        "isFeatured": false
    },
    {
        "sku": "FB4315-100",
        "name": "Nike Air Max 90 SE",
        "price": 140.00,
        "description":"Step into the history books. Paying homage to Frank Rudy, the man who created the coveted cornerstone of cushioning—Air—these sneakers celebrate his legacy with fun details.",
        "images": ["https://static.nike.com/a/images/t_PDP_864_v1/f_auto,b_rgb:f5f5f5/67cf2b36-73ef-443a-8e99-a496eff525d6/air-max-90-se-mens-shoes-fSGj72.png"],
        "category": "Men",
        "style" : "Men's Shoes",
        "isNew": false,
        "onSale": false,
        "isFeatured": false
    },
    {
        "sku": "FD0868-133",
        "name": "Nike Dunk Low SE",
        "price": 110.00,
        "description":"Lace up and make your mark in shoes that carry a legacy. A legend in the basketball world and an icon in skate culture, the Nike Dunk has been a sneaker favorite for decades.",
        "images": ["https://static.nike.com/a/images/t_PDP_864_v1/f_auto,b_rgb:f5f5f5/26e69356-9de4-4b43-acfe-8d7037631363/dunk-low-se-womens-shoes-wXTkMh.png" , "https://static.nike.com/a/images/t_PDP_864_v1/f_auto,b_rgb:f5f5f5/8d52f916-021b-4c12-9cfa-049943f2b7d2/dunk-low-se-womens-shoes-wXTkMh.png"],
        "category": "Women",
        "style" : "Women's Shoe",
        "isNew": false,
        "onSale": false,
        "isFeatured": false
    },
    {
        "sku": "FD0867-133",
        "name": "Air Max 90 SE",
        "price": 120.00,
        "description": "Lace up and make your mark in sneakers that carry a legacy. Produced at the intersection of art, music and culture, this champion running shoe helped define the '90s. Worn by presidents, revolutionized through collabs and celebrated with rare colorways, its striking visuals, Waffle outsole and exposed Air cushioning help keep it alive and well decades later. A durable canvas upper gives this special edition a new look and feel while screen-printed graphics celebrate the future.",
        "images": ["https://static.nike.com/a/images/t_PDP_864_v1/f_auto,b_rgb:f5f5f5/0c5a8acb-50e6-4802-a822-461cfacb15f1/air-max-90-se-womens-shoes-b7KjQn.png"],
        "category": "Women",
        "style": "Women's Shoes",
        "isNew": false,
        "onSale": false,
        "isFeatured": false
    },
    {
        "sku": "DO8863-600",
        "name": "Jordan Sophia",
        "price": 100.00,
        "description": "Plush comfort is a must for your winter wardrobe—and footwear is no exception. These luxe slides have pillowy, criss-cross straps lined with fabric that feels soft against your skin.",
        "images": ["https://static.nike.com/a/images/t_PDP_864_v1/f_auto,b_rgb:f5f5f5/b3831dc7-7151-4fb4-82a3-d74306e9706a/jordan-sophia-womens-slides-bW5vFq.png", "https://static.nike.com/a/images/t_PDP_864_v1/f_auto,b_rgb:f5f5f5/64aeb2bf-d26b-4f94-9fd3-49c4b79f5822/jordan-sophia-womens-slides-bW5vFq.png"],
        "category": "Women",
        "style": "Women's Slide",
        "isNew": false,
        "onSale": false,
        "isFeatured": false
    },
    {
        "sku": "DV1033-100",
        "name": "Nike Offcourt Adjust",
        "price": 60.00,
        "description": "Post game, errands and more—adjust your comfort on the go. The adjustable, padded strap lets you perfect your fit, while the lightweight foam midsole brings first-class comfort to your feet.",
        "images": ["https://static.nike.com/a/images/t_PDP_864_v1/f_auto,b_rgb:f5f5f5/d1d9f856-745f-463a-98ef-8e90bb83b0d0/offcourt-adjust-womens-slides-PLGCnm.png"],
        "category": "Women",
        "style": "Women's Slides",
        "isNew": false,
        "onSale": false,
        "isFeatured": false
    },
    {
        "sku": "DV7762-100",
        "name": "Nike Air Force 1",
        "price": 100.0,
        "description": "The Nike AF1s are a legend. First on the basketball courts in the '80s. Now wearable everywhere from school to the playground. They've been an icon for decades\u2014meaning a long time! Smooth durable leather lasts for many days of play. Fun colors bring an extra push to get you moving outside.",
        "images": [
          "https://static.nike.com/a/images/t_PDP_1280_v1/f_auto,b_rgb:f5f5f5/172ed7f4-7b37-4424-8019-85592086d89c/air-force-1-big-kids-shoes-km6NJj.png",
          "https://static.nike.com/a/images/t_PDP_1280_v1/f_auto,b_rgb:f5f5f5/52bafb26-0e4e-4023-98c7-714b664314e1/air-force-1-big-kids-shoes-km6NJj.png",
          "https://static.nike.com/a/images/t_PDP_1280_v1/f_auto,b_rgb:f5f5f5/0ed6d2af-7c52-4a55-a004-f31fd054425c/air-force-1-big-kids-shoes-km6NJj.png",
          "https://static.nike.com/a/images/t_PDP_1280_v1/f_auto,b_rgb:f5f5f5/42dd113c-51e1-47d9-be3b-6252c5080bdb/air-force-1-big-kids-shoes-km6NJj.png",
          "https://static.nike.com/a/images/t_PDP_1280_v1/f_auto,b_rgb:f5f5f5/c23256d2-8400-4d97-8292-40bf9bae0bef/air-force-1-big-kids-shoes-km6NJj.png",
          "https://static.nike.com/a/images/t_PDP_1280_v1/f_auto,b_rgb:f5f5f5/f861d1c8-5c32-40db-acc0-55d0800919ed/air-force-1-big-kids-shoes-km6NJj.png",
          "https://static.nike.com/a/images/t_PDP_1280_v1/f_auto,b_rgb:f5f5f5/1d31f0ca-b3a2-41b1-8f94-d425daf2475b/air-force-1-big-kids-shoes-km6NJj.png",
          "https://static.nike.com/a/images/t_PDP_1280_v1/f_auto,b_rgb:f5f5f5/c0f019a6-87f6-4679-adff-585a7ba862a1/air-force-1-big-kids-shoes-km6NJj.png"
        ],
        "category": "Kids",
        "style": "Big Kids' Shoes",
        "isNew": false,
        "onSale": false,
        "isFeatured": false
    },
    {
        "sku": "DV3607-101",
        "name": "Nike Air Max 90 LTR",
        "price": 100.0,
        "description": "The Air Max 90 returns with an even better feel for you. Cushioning is softer and more flexible than previous versions, the Max Air unit is tuned for growing feet and the shape gives your toes more wiggle room. With a design and look that are still the same, it brings a '90s fave to a new generation.",
        "category": "Kids",
        "style": "Big Kids' Shoes",
        "images": [
          "https://static.nike.com/a/images/t_PDP_1280_v1/f_auto,b_rgb:f5f5f5/0976169b-51e4-44d7-91cd-b3b1bc76e37b/air-max-90-ltr-big-kids-shoes-1wzwJM.png",
          "https://static.nike.com/a/images/t_PDP_1280_v1/f_auto,b_rgb:f5f5f5/8f11cef6-f507-4419-ab7c-fba99353798a/air-max-90-ltr-big-kids-shoes-1wzwJM.png",
          "https://static.nike.com/a/images/t_PDP_1280_v1/f_auto,b_rgb:f5f5f5/f8695135-4416-4ecb-98c7-6314b0f3cb1f/air-max-90-ltr-big-kids-shoes-1wzwJM.png",
          "https://static.nike.com/a/images/t_PDP_1280_v1/f_auto,b_rgb:f5f5f5/feaab381-0f05-44ec-b6b3-d633e29b2b43/air-max-90-ltr-big-kids-shoes-1wzwJM.png",
          "https://static.nike.com/a/images/t_PDP_1280_v1/f_auto,b_rgb:f5f5f5/e91c8eef-97a6-4fff-9e1e-2c3416905abd/air-max-90-ltr-big-kids-shoes-1wzwJM.png",
          "https://static.nike.com/a/images/t_PDP_1280_v1/f_auto,b_rgb:f5f5f5/6a5bc611-a537-47db-9834-5f85f839a824/air-max-90-ltr-big-kids-shoes-1wzwJM.png",
          "https://static.nike.com/a/images/t_PDP_1280_v1/f_auto,b_rgb:f5f5f5/25211595-c549-4e11-a225-0b9f9f38b960/air-max-90-ltr-big-kids-shoes-1wzwJM.png",
          "https://static.nike.com/a/images/t_PDP_1280_v1/f_auto,b_rgb:f5f5f5/cf8e4f87-8aee-4964-ad35-01c8d3734826/air-max-90-ltr-big-kids-shoes-1wzwJM.png",
          "https://static.nike.com/a/videos/t_PDP_1280_v1/f_auto,b_rgb:f5f5f5,so_2.4/51431284-10fb-43b6-aa82-2a55040f5ea3/air-max-90-ltr-big-kids-shoes-1wzwJM.jpg"
        ],
        "isNew": false,
        "onSale": false,
        "isFeatured": false
    },
    {
        "sku": "DH4084-001",
        "name": "Nike Air VaportMax 2021 FK",
        "price": 210.00,
        "description":"Made from at least 40% recycled materials by weight, the Nike Air VaporMax 2021 FK is airy and easy to wear with superstretchy, recycled Flyknit fabric (plus a soft collar that sculpts your ankle).",
        "images": ["https://static.nike.com/a/images/t_PDP_1280_v1/f_auto,b_rgb:f5f5f5/6b7918cc-f111-42ae-862a-e37b8d3ead6b/air-vapormax-2021-fk-mens-shoes-NpTfFz.png"],
        "category": "Men",
        "style" : "Men's Shoes",
        "isNew": false,
        "onSale": true,
        "isFeatured": false
    },
    {
        "sku": "DZ5221-100",
        "name": "Nike Pegasus Turbo Next Nature",
        "price": 150.00,
        "description":"Log the hard miles with the Nike Pegasus Turbo Next Nature. These thoughtfully made stallions use Flyknit technology to bring you a stretchy, just-right feel up top. Lightweight and responsive ZoomX foam is designed to help you increase tempo without having to sacrifice comfort.",
        "images": ["https://static.nike.com/a/images/t_PDP_1280_v1/f_auto,b_rgb:f5f5f5/8a33eb97-d773-4527-95cb-228818675c7f/pegasus-turbo-next-nature-womens-road-running-shoes-v0hK3R.png"],
        "category": "Women",
        "style" : "Women's Running Shoes",
        "isNew": false,
        "onSale": true,
        "isFeatured": false
    }   
]